{"cyK58ZMB8x9OZnfA2rtEFg==":"penkr%20cig-1836x2262.png","dtMWVz6urvjP5oqdrJ4HnQ==":"penkr%20cig-829x1021.png","tx/t+r7tSawOL2PnCIZOzA==":"collage%20cars%20banner-612x208.png","AOkx7ifduSWELNB/xF8Ltw==":"collage%20cars%20copy-2216x627.jpg","aLdbImDiVZO6Pr4yqogmSQ==":"collage%20cars%20copy-2216x627.jpeg","Jx7AkxpHtsZNMyeqHaHWuQ==":"penkr%20falcon-96x60.png","LmuxJUN+0JmqLpd8N8eJuw==":"cn&en%20logo-1076x1076.png","JmH4TM6te5oDP+fu3LF9RA==":"penkr%20falcon-696x434.png","911X7bM4yT2Mobv6BsMc+g==":"background8.jpg","IHNQjocJela7wqpcN3XplQ==":"asset%2031-1076x937.png","VyIcVed7WkiUe8ZL7E4WSQ==":"img-395-1076x1344.jpg","Tpu5GwMR1/VY9bg7xIcUJQ==":"asset%2032-1076x1076.png","AC/GwVbTId6+lIV0YMqsEA==":"dsc09625-1076x957.jpeg","bg8fNJYfABuSsWAj2GDeew==":"asset%2032-1076x1076.png","6LXmSnjIQ/1GqW5Y7WiPtw==":"penkr%20cig-606x747.png","qc7CbDpzhK5P7Xgn8HL4ow==":"asset%2034-606x606.png","hyBAY9wL5lGmRNS7S4QrFQ==":"asset%2033-606x614.png","J9SiVKMMIYgrzTwxjsRA9A==":"asset%2032-606x606.png","+qlx+mQx/9P6FOTu/xB6HA==":"asset%2035-606x654.png","BRkNTv7J+0tYR/e54V9b1g==":"img-810-829x819.jpg","qm5pC+IN3ZSdn/QW8DQHXA==":"img-810-1284x1269.jpg","LOiGofgpL5ugIL2Cry4WIA==":"640-829x915.jpg","4lVSr5lagtq1Emh9ECEK8A==":"640-1-829x915.jpg","KusB9hVVbinROD9/vpqWKw==":"640%202-829x467.jpg","+eUYIybZUVuoWDnxHK/4pQ==":"640-5-829x467.jpg","wIrxpX11QKrn7Au2BecnPQ==":"640-21.webp","N6w9nDHwYskiCTE9gkPCTg==":"640-22.webp","//Ukl/TDR0mwnYWg+ugJ5Q==":"aea-585x208.png","xeTcwz0/o0MPoaco+NLVAA==":"640-2.jpeg","HAbKQTb1S82TN0TSD8cCwg==":"640-1.jpeg","tyKKoxuSTNzBvHgFK/c/Jw==":"collage-cars-copy.jpeg","DHXPAmvZz8LyTEYe/kgx9Q==":"640-6.jpeg","VS8wHLfwTN1CnovrA1Ya+g==":"collage-cars-copy-1.jpeg","7vFUqO/SocemlsbKfW9FzA==":"cnen-logo-1.png","8pQmy3HSwuxPwHoKf/AC7g==":"cnen-logo-transparent-large.png","oRykAiO0rUD++7AmPeEwUg==":"background1.jpg","F2VZG1WvJ/QCoMRmXUFauw==":"cnen-blk-bg-1-large.jpeg","jfgBfglxw2KIkX91XW6Now==":"0000ffblue-172x129.png","7brTIF2lRptklnu26BlgZw==":"yellow-172x129.png","8cLVEz2KPlZsObeFG3zBpQ==":"greycccccc-172x129.png","XgbLU/DaxYquko35r7GmYA==":"whtffffff-172x129.png","znj0Z8DRFpv3XIMaY0mHIg==":"green00ff00-172x129.png","2v4JUBQJRH9XTVtQBJUBZA==":"orange-cirle-1-357x358.png","kaAoq6RQJm6Z1/ZqvRtQtA==":"background2-1.jpg","Hi+SgQ+tLcY8wm2h8LTSsg==":"kinforest.png","yvYRK1CA33bBDbtGAcWBOA==":"eddystar..png","xczrdUduUx2FZDaOHpH7+Q==":"eddystar.-1.png","xJFS3tK9oKBzdc2nZeDhoQ==":"asset-11.png","95K/YQcdVhe4smOUGbj+sQ==":"asset-13.png","Yfzp6G8zOiL3OQsQIhELiQ==":"asset-9.png","S0Vats0bR6jrLELcBGEnWg==":"asset-14.png","hd4aF3xWA9DraaBYod+B4A==":"asset-15.png","HpB80zqPvwZDYQY1MvlBvQ==":"640-5.jpeg","2n+EsuLk2M+vtd3V1HxTig==":"640-3.jpeg","ZAzdrOMTgclkHpj4f23qqQ==":"img-1031.jpg","NjXrLJbBNEo2BkDhh0Q0Aw==":"640-4.jpeg","nbolk4oZwhLoJ62FIyFCyg==":"640-7.jpeg","U2ENzcl9ZTVUeuAgP61+1A==":"640-8.jpeg","pjwJmWRDJ+1LUWeO3/s4+A==":"640-9.jpeg","jjhR7KR1fhLhlbwHvq3Djg==":"640-10.jpeg","7slU1E/j1cq1zu5D5diIbQ==":"640-11.jpeg","Ju4J57Pfm0QVZerUXTfAAw==":"640-12.jpeg","h7KaoN0S4EYk0yL4BIvyvw==":"fc%20nobg-506x506.png","CmHEwgWbLnKuArCJ4j3sWw==":"halt-word-logo-696x709.png","e7xJTkCL3GoytIaxN0Ge+w==":"cton!-icon-506x526.png","HBpCen8r23IsYIPyetH09g==":"img-8375-696x851.jpg","Vb7GgbMoe0curpGYBParsg==":"background3-1.jpg","iDE9wNwesiZtB5u5TgEEJg==":"penkrpk.png","o2l3BqBZW6d1a/RigJJEWA==":"asset-29.png","oXXEZSGPQFegecRGgcuKJA==":"product-catalogue.png","tPFykNbCLcnRR/gBhbm0aQ==":"ctc-penkr-future-1.png","BCcgE5dpPgV79gCmj54e+g==":".png","63sXAN/4mHkXCKZAZLI3Jw==":"img-8578.jpg","h37+MHpSxcN/0K74OGDLMA==":"snapseed-11.jpg","mzuray+3DtKubHCzCZMufg==":"img-1525.jpg","UbDVr9JYcsdQdHYaylEj4Q==":"snapseed-10.jpg","rHGKlaBTDQbNZ8Ph7V/CSw==":"snapseed-12.jpg","9oLKMydCb5H4P7Bjue/tdQ==":"pastedgraphic.png","sjHxoafI/vZxU1GIyjkYng==":"sq2.jpg","hj0RQkK8yqcYhDaeD2Z96A==":"mbr.jpg","v9FKfJK/unNVIyGwAfKaqQ==":"mbr-1.jpg","WSgLvu76ewvjcLYeXiDeeg==":"1821645020908-.pic-hd.jpg","1Hhy4Gi5nAc5+qcf7zcNpA==":"img-1612.jpg","5K9rE909L6phiNqb3pTrxQ==":"img-1574.jpg","Wf/DGDibN4GKgBCcVVuhyg==":"img-1614.jpg","eBuuX/7KFS2l0WcKSIfMTw==":"pk.png","rx7W5LQhWgNNrmXmriEq1w==":"img-474.jpg","ccJVcyVzN0M5+uakLxwL7w==":"img-474.jpeg","kgtRUPFYiSOa0Zy3rLhVcw==":"img-475.jpeg","ftKPojpcV5CsrDHueCtaFg==":"asset-31.png","VHgZknV8IqaLcNuuLK2KwQ==":"asset-30.png","NMvCo6HHfw1OsJmti/UX2w==":"asset-32.png","NUUdiqmfXyvnv5TNINswOA==":"img-1031.jpeg","BSeskSWjmyxORCS2IR127Q==":"dsc09618.jpg","MmUz6t+zRts7acx0+UOb3A==":"dsc09618.jpeg","WfZ73HTIJJMmidEvaxQ2aA==":"asset-16.png","TejG/bIfbi8Dd6/DmobN2Q==":"asset-17.png","g2Dwz7UH7vV+COVVJwhc5A==":"xpeng-800-volt-charging-100812251-h.jpg","hagB3zVTUUxkUkv4ra6VxQ==":"dsc09627.jpg","Ixj/bJTHSjPXlBKGekcIkA==":"penkr-bubba-p7-vinyl-wrap.png","Io/lM/Ev1NuyFp/EofLCSA==":"chinese-shufa-wht-bg.png","lsC4LIydtayXpK179/DAOA==":"img-1563.jpg","Xy6fANwnE5wnLA4Sqj8IIQ==":"img-1563.jpeg","Kk+BkZeHkE7ekclraT8NRQ==":"img-1614.jpeg","hA5SH42jBO2yS4vXC5y1Wg==":"img-2321.jpeg","2iyr44DGzmVsTBYBEApYBg==":"dsc09621.jpg","fCrVqox8Yu90LEFhmTAzWw==":"img-1122.jpg","tnTkNt6f+mOZ1ITqa319vg==":"dsc09612.jpg","iu2ocLti2WyZWPHK+NeBNw==":"dsc09610.jpg","XO5ASXKB0BZB/shaz77kJw==":"640-13.jpeg","s8NXgloFzJTJFOmkLx7J/Q==":"img-1615.jpeg","noQbrrgJrewmJwVpeEnPaw==":"422aad42-bfed-453b-8b8c-c6b386a179d0.jpg","RgoQeIHhhvL1CwbXuInW4w==":"pasted-graphic-6.png","tu0VM6zepv/FtKwK2Ajx8A==":"pasted-graphic-5.png","yQ3gSYelXceBjpdNpcdAng==":"pasted-graphic-3.png","J7TfARkrmMPCOSkmbpcTZQ==":"img-1562.jpg","nkEEWu5HBLSuws9mmQ6oBA==":"img-8579.jpg","h1YbQhWn3vhrsEdtqYrGnw==":"img-1443.jpg","wH6mvYS0gNqKe01ilfcMcQ==":"cn&en%20logo-1076x1076.png","mjSeRDc5QDNxEZ/B0RBg5Q==":"asset-28.png"}